easyID3/__init__.py
easyID3/node.py
easyID3/tree.py
easyID3-0.1.5.dist-info/LICENSE
easyID3-0.1.5.dist-info/METADATA
easyID3-0.1.5.dist-info/WHEEL
easyID3-0.1.5.dist-info/top_level.txt
easyID3-0.1.5.dist-info/RECORD
